[{"run_id": 9223370488251810107, "name": "run from keep", "distance": 4061.318858924423, "moving_time": "0:39:08", "type": "Run", "start_date": "2019-01-27 14:28:12", "start_date_local": "2019-01-27 22:28:12", "location_country": "{'latitude': 29.579717339409722, 'longitude': 106.54048014322916, 'country': '\u4e2d\u56fd', 'nationCode': '156', 'province': '\u91cd\u5e86\u5e02', 'city': '\u91cd\u5e86\u5e02', 'cityCode': '023', 'district': None, 'districtCode': None}", "summary_polyline": "", "average_heartrate": null, "average_speed": 1.7296928700700267, "streak": 1}, {"run_id": 9223370479884641507, "name": "run from keep", "distance": 1215.864324616284, "moving_time": "0:19:02", "type": "Run", "start_date": "2019-05-04 11:23:08", "start_date_local": "2019-05-04 19:23:08", "location_country": "{'latitude': 29.554186197916668, 'longitude': 106.53833930121527, 'country': '\u4e2d\u56fd', 'nationCode': '156', 'province': '\u91cd\u5e86\u5e02', 'city': '\u91cd\u5e86\u5e02', 'cityCode': '023', 'district': None, 'districtCode': None}", "summary_polyline": "iojsDiceiSAI?GAC?EACAE@AAC?EAA?GAGAE?GAK@??IAG@GAWAGCMCIAECO?E?GCOCQ?C@GESAMIk@?GCECECK?GAKAE?IAGAI@EHO?@ACAC?GGSCEEIAECOAECGEUCGCGAICEAO@e@KQ?IAGAOA]?IAOCICC@G?GEGGMAQCIAIAKCE?OESEK@ECECCAQAEAGAIAGAECQIOAGCEAGAGAECEEOCCAGAEEIAEACCMCGAGCGCI?GACCE?EEKACCGAEAQCOCCEIAEAGAEAECGGQACEKACAIAIIKEGCCEICCAIAGEOEMCCAGEGCIAECEGOCGAEAICGAGAGEOEGEICEACCICEKQAICCEIAE?K?CCIAQGIACEMMSACAECGCGFAACCCGIEQCAEOCGEEEMAE?MKOEGCG?AEEAECGGMCGAECGAEKKCCCGECKMCIAGKIEEEGCCCEGGEECIGECEKOEECGECACQOEGAAII@?@AAAA?A?AC@C?A?A?A??", "average_heartrate": null, "average_speed": 1.064679793884662, "streak": 1}, {"run_id": 9223370479100449707, "name": "run from keep", "distance": 3123.167883331343, "moving_time": "0:21:10", "type": "Run", "start_date": "2019-05-13 13:10:56", "start_date_local": "2019-05-13 21:10:56", "location_country": "{'latitude': 29.561031629774305, 'longitude': 106.54379448784722, 'country': '\u4e2d\u56fd', 'nationCode': '156', 'province': '\u91cd\u5e86\u5e02', 'city': '\u91cd\u5e86\u5e02', 'cityCode': '023', 'district': None, 'districtCode': None}", "summary_polyline": "ivosD}cgiSFNT`@\\\\b@d@LVP~BBHDPBA?ALGPIBED_@HG^Df@HLF\\B`@ATCd@I|BQHUDkAk@mA@B?X?B??DTFLFHJp@?L@LHRDDHFFDFBFPHNd@xAl@|ALN\\f@b@`Bb@j@BZ@C?CfGcApAc@h@[bD}AX_@\\YNITQNGNM\\[JI~@c@NEh@Ij@OTQHQX_@RMTE`A]DGDE?C@E?CPA`@ENCTA^ELCPC`@ILAnAIP?RGLADA@@T@d@Bl@MRBL@\\HBAdAAf@INEb@MPGNC`@UNGl@o@JOZm@Ve@JOViAHQPk@DUJa@HUNg@DUNk@JYPu@HSLi@BSNe@DQNg@JWPk@FULe@FWBOPk@DOLe@FQBMDQBEBa@KMGEEECMBG@EHI\\CrBzDI?A?s@sB[]Wj@CFEIn@XCLKDGDLCED?F?@@CF@z@IHg@\\m@Ug@q@Q??BA??GCAAA?", "average_heartrate": null, "average_speed": 2.4591873097097188, "streak": 1}, {"run_id": 9223370472274439307, "name": "run from keep", "distance": 5853.31330625389, "moving_time": "0:32:45", "type": "Run", "start_date": "2019-07-31 13:06:04", "start_date_local": "2019-07-31 21:06:04", "location_country": "{'latitude': 29.56207248263889, 'longitude': 106.57729844835069, 'country': '\u4e2d\u56fd', 'nationCode': '156', 'province': '\u91cd\u5e86\u5e02', 'city': '\u91cd\u5e86\u5e02', 'cityCode': '023', 'district': None, 'districtCode': None}", "summary_polyline": "", "average_heartrate": null, "average_speed": 2.978785397584677, "streak": 1}, {"run_id": 9223370463205605407, "name": "run from keep", "distance": 3223.046854210085, "moving_time": "0:20:03", "type": "Run", "start_date": "2019-11-13 12:25:58", "start_date_local": "2019-11-13 20:25:58", "location_country": "{'latitude': 29.583243001302083, 'longitude': 106.5374490017361, 'country': '\u4e2d\u56fd', 'nationCode': '156', 'province': '\u91cd\u5e86\u5e02', 'city': '\u91cd\u5e86\u5e02', 'cityCode': '023', 'district': None, 'districtCode': None}", "summary_polyline": "o`qsDgegiS{@Ew@Cw@Cq@CYA_A?kAlAQl@Gp@ARD`BHXVd@\\^h@Rr@Fn@Ff@@VAb@@n@IVEz@g@T_@JyE_@wAiA]iA?ODWAI@UBIAG?c@@S@W?K@U?s@l@GPQf@Ox@?xAX~@\\`@f@^r@PjBHl@CRAp@EVGf@SLM^gAN}AQiBGQe@_AQEK?U@a@?I?I?I?S?MAK?IAS@IAK?K@_@?WAKAWBe@Fg@XITELEJCLI\\Ct@JjBVj@LL\\Zp@Vn@Dh@@t@@VAl@Al@G`Ak@Ri@RiAEy@Ei@@YMc@O[AM@GMOUEE?GASCKBIAU?i@?I?K?IAG@O@KCI?G?I?GAQ?Q@SBS?G?G?G@SBGBIDGDOJEHCFETETIt@At@H~@Z`ApAv@l@FP@~@BV?h@ANANB\\EJCPKFEHE`@]BEDGBEHW@IBK?GBKH[@IBSAGBCEG?ECO?Q?GMY", "average_heartrate": null, "average_speed": 2.679174442402398, "streak": 1}, {"run_id": 9223370463118829207, "name": "run from keep", "distance": 2025.3293695480431, "moving_time": "0:13:30", "type": "Run", "start_date": "2019-11-14 12:38:52", "start_date_local": "2019-11-14 20:38:52", "location_country": "{'latitude': 29.585864800347224, 'longitude': 106.53690402560764, 'country': '\u4e2d\u56fd', 'nationCode': '156', 'province': '\u91cd\u5e86\u5e02', 'city': '\u91cd\u5e86\u5e02', 'cityCode': '023', 'district': None, 'districtCode': None}", "summary_polyline": "o~psD{dgiSaAO{@CgCAy@?q@?qAnAIVOx@E^FpARb@NN\\Zn@Vd@NZFl@DRAb@EX?l@GbAe@NS^{AB[YiDm@e@QCeCIsB?oAR[h@GPMh@EXEp@RnBb@v@^PzA\\R?n@@bAGj@CVEv@_@NQHSJWNSBY?G?I@WCGAY@I@KE[EIOUg@gACGICICQE[GYEGB[?G@OBOAQAMBG?GDK@G?O@c@@G?K?O@S?I?QDEHMLIVIZEFCFGHCPCR?T?FBL@J@BALABADA@A@?@?BIJMBCQDI", "average_heartrate": null, "average_speed": 2.5004066290716582, "streak": 2}, {"run_id": 9223370458275667607, "name": "run from keep", "distance": 3017.4332527391734, "moving_time": "0:25:17", "type": "Run", "start_date": "2020-01-09 13:46:28", "start_date_local": "2020-01-09 21:46:28", "location_country": "{'latitude': 29.583356119791667, 'longitude': 106.53764702690972, 'country': '\u4e2d\u56fd', 'nationCode': '156', 'province': '\u91cd\u5e86\u5e02', 'city': '\u91cd\u5e86\u5e02', 'cityCode': '023', 'district': None, 'districtCode': None}", "summary_polyline": "", "average_heartrate": null, "average_speed": 1.9890792700983344, "streak": 1}, {"run_id": 9223370458020558807, "name": "run from keep", "distance": 4547.989183462619, "moving_time": "0:33:07", "type": "Run", "start_date": "2020-01-12 12:30:27", "start_date_local": "2020-01-12 20:30:27", "location_country": "{'latitude': 29.58483968098958, 'longitude': 106.53598442925347, 'country': '\u4e2d\u56fd', 'nationCode': '156', 'province': '\u91cd\u5e86\u5e02', 'city': '\u91cd\u5e86\u5e02', 'cityCode': '023', 'district': None, 'districtCode': None}", "summary_polyline": "e_qsDcegiS]Cc@CSDc@Bm@Ck@CmC@iAbBM`ACPGj@?^\\bAFJ`@^f@R~@@PB`@FT?zAIh@U`Ak@\\g@Pi@?o@Cq@k@iBEMU]eBIQ?i@AsA@U?g@?UBk@\\Wn@GNIb@Ij@AVDv@BVZ|@TT`@TPDf@Hz@DT?f@Az@CTGb@UxAmAJqA?m@Ci@Sq@GO_Au@M?KAo@Bi@B_AGs@ASA}@La@`@c@rAKf@AX@v@BNDPLd@X^\\T`AT^BV@d@BP@n@Af@Ef@QRGZ[b@o@JUFm@AS?y@DYIMGUEGEICKEEAEEGAECECIEIEA@A]QKCi@HOH@@KEI??AC@EAC@A?IBYDIEC?QCE?MDKDC@MDe@]GAE?I@C?O@IDMLGBKFYVGRAHAJ@PAB@HAFCJCP?HAL@H?H?HAB?DAFBL?L?HHFADFFBDDLFLHJBFDFFFBFHDB@LNRBB@H?NFLBD?DAP@DEF?DAF?JBJBD@HAF?D@FAD@DCJ@F?BAHADAH?NCFCFCNEDCFEFEBCJIBEBC@G@IHGHCBCNILKBSEc@@KBC?OAM@CBGASCI?ICQEKIOEIAG?GEEACEMAISMQCi@GQ?g@A}@?g@GQ?g@AS?_@Hc@N_@X]n@MbBNfABLJb@\\`@VRRJnAPhAJR@`@C\\E`@KLEVONMl@u@L]H}@@y@Gc@Qq@GKEM]e@[CUBe@AUC_AC_@ES?m@COBo@JsA`BKx@ARBh@Hb@DTXt@VZFHz@XPDF?B@F@", "average_heartrate": null, "average_speed": 2.2888722614306083, "streak": 1}, {"run_id": 9223370457847258107, "name": "run from keep", "distance": 1948.6118447662625, "moving_time": "0:15:31", "type": "Run", "start_date": "2020-01-14 12:56:25", "start_date_local": "2020-01-14 20:56:25", "location_country": "{'latitude': 29.585746256510415, 'longitude': 106.53633382161458, 'country': '\u4e2d\u56fd', 'nationCode': '156', 'province': '\u91cd\u5e86\u5e02', 'city': '\u91cd\u5e86\u5e02', 'cityCode': '023', 'district': None, 'districtCode': None}", "summary_polyline": "eaqsDmdgiSyAK{Bp@}B?e@bAAfBDTLh@xA|@|BXTAbACTCx@]ROd@y@Pe@KeAC{@CMGOYg@{AJcAEkBFo@AkBv@j@bFNFrBl@N@dCEl@Qj@YJKFEFIJU@E@UAIDG@K@GA[EC?KHQFQAGE]GGEGEGIIEOCGKOGIGEOGC@G?EBAAGACA_@FO@G?OCOEEAGEI@QBM?OCSEU?QDK@S?Q@CBIDE@QHEAKRA?CFE@IH?D?FAB?BCPCRCHEDCL@L?F?\\CJ@HC@CD@@ET?DANAHBJ?F?JA@?@??????????????????@?@ACA", "average_heartrate": null, "average_speed": 2.0930309825631177, "streak": 1}, {"run_id": 9223370457587809307, "name": "run from keep", "distance": 1769.4655118956398, "moving_time": "0:10:20", "type": "Run", "start_date": "2020-01-17 13:05:46", "start_date_local": "2020-01-17 21:05:46", "location_country": "{'latitude': 29.584193250868054, 'longitude': 106.53807698567708, 'country': '\u4e2d\u56fd', 'nationCode': '156', 'province': '\u91cd\u5e86\u5e02', 'city': '\u91cd\u5e86\u5e02', 'cityCode': '023', 'district': None, 'districtCode': None}", "summary_polyline": "{~psD}dgiSE?WAm@Au@C{@?y@Cm@A_@?U?iAn@Sn@KlAEb@^|BfAn@d@Lz@ATApA@bB[x@wAR_BWsBcA_Am@@uA@s@CSB{AJ}@d@Qh@CNMbBj@bCLLxA`@xABl@En@A~@ObA}@TmDi@mBCGAEIIIAGCO@I?G@I?UASEGBK?GBSAE?M[?@?AFP^K@?", "average_heartrate": null, "average_speed": 2.8539766320897417, "streak": 1}, {"run_id": 9223370457500833307, "name": "run from keep", "distance": 2297.37838368795, "moving_time": "0:14:17", "type": "Run", "start_date": "2020-01-18 13:11:21", "start_date_local": "2020-01-18 21:11:21", "location_country": "{'latitude': 29.58306803385417, 'longitude': 106.53779486762153, 'country': '\u4e2d\u56fd', 'nationCode': '156', 'province': '\u91cd\u5e86\u5e02', 'city': '\u91cd\u5e86\u5e02', 'cityCode': '023', 'district': None, 'districtCode': None}", "summary_polyline": "", "average_heartrate": null, "average_speed": 2.6807215678972582, "streak": 2}]